omicscheck/__init__.py
omicscheck/analyzer.py
omicscheck/cli.py
omicscheck/downloader.py
omicscheck/logger.py
omicscheck/parser.py
omicscheck/qa_score.py
omicscheck/reporter.py
omicscheck/utils.py
omicscheck/visualizer.py
omicscheck-1.0.2.dist-info/licenses/LICENSE
omicscheck-1.0.2.dist-info/METADATA
omicscheck-1.0.2.dist-info/WHEEL
omicscheck-1.0.2.dist-info/entry_points.txt
omicscheck-1.0.2.dist-info/top_level.txt
omicscheck-1.0.2.dist-info/RECORD
