Metadata-Version: 2.4
Name: omicscheck
Version: 1.0.2
Summary: A lightweight tool to inspect GEO series matrices online before downloading.
Author-email: AHMED YASSIN || COMPUTATIONAL BIOLOGIST <ahmedyassin300@outlook.com>
License-Expression: MIT
Requires-Python: >=3.8
License-File: LICENSE
Requires-Dist: pandas
Requires-Dist: requests
Requires-Dist: matplotlib
Requires-Dist: seaborn
Requires-Dist: fpdf
Requires-Dist: typer
Requires-Dist: rich
Requires-Dist: scikit-learn
Dynamic: license-file
